azure/opentelemetry/exporter/azuremonitor/__init__.py
azure/opentelemetry/exporter/azuremonitor/_connection_string_parser.py
azure/opentelemetry/exporter/azuremonitor/_options.py
azure/opentelemetry/exporter/azuremonitor/_storage.py
azure/opentelemetry/exporter/azuremonitor/_utils.py
azure/opentelemetry/exporter/azuremonitor/_version.py
azure/opentelemetry/exporter/azuremonitor/_generated/__init__.py
azure/opentelemetry/exporter/azuremonitor/_generated/_azure_monitor_client.py
azure/opentelemetry/exporter/azuremonitor/_generated/_configuration.py
azure/opentelemetry/exporter/azuremonitor/_generated/aio/__init__.py
azure/opentelemetry/exporter/azuremonitor/_generated/aio/_azure_monitor_client.py
azure/opentelemetry/exporter/azuremonitor/_generated/aio/_configuration.py
azure/opentelemetry/exporter/azuremonitor/_generated/aio/operations/__init__.py
azure/opentelemetry/exporter/azuremonitor/_generated/aio/operations/_azure_monitor_client_operations.py
azure/opentelemetry/exporter/azuremonitor/_generated/models/__init__.py
azure/opentelemetry/exporter/azuremonitor/_generated/models/_azure_monitor_client_enums.py
azure/opentelemetry/exporter/azuremonitor/_generated/models/_models.py
azure/opentelemetry/exporter/azuremonitor/_generated/models/_models_py3.py
azure/opentelemetry/exporter/azuremonitor/_generated/operations/__init__.py
azure/opentelemetry/exporter/azuremonitor/_generated/operations/_azure_monitor_client_operations.py
azure/opentelemetry/exporter/azuremonitor/export/__init__.py
azure/opentelemetry/exporter/azuremonitor/export/_base.py
azure/opentelemetry/exporter/azuremonitor/export/trace/__init__.py
azure/opentelemetry/exporter/azuremonitor/export/trace/_exporter.py
azure_opentelemetry_exporter_azuremonitor-1.0.0b2.dist-info/LICENSE.txt
azure_opentelemetry_exporter_azuremonitor-1.0.0b2.dist-info/METADATA
azure_opentelemetry_exporter_azuremonitor-1.0.0b2.dist-info/WHEEL
azure_opentelemetry_exporter_azuremonitor-1.0.0b2.dist-info/top_level.txt
azure_opentelemetry_exporter_azuremonitor-1.0.0b2.dist-info/RECORD
